quantflow/__init__.py
quantflow/data/__init__.py
quantflow/data/fetcher.py
quantflow/options/__init__.py
quantflow/options/black_scholes.py
quantflow/risk/__init__.py
quantflow/risk/metrics.py
quantflow_finance-0.1.10.dist-info/licenses/LICENSE
quantflow_finance-0.1.10.dist-info/METADATA
quantflow_finance-0.1.10.dist-info/WHEEL
quantflow_finance-0.1.10.dist-info/top_level.txt
quantflow_finance-0.1.10.dist-info/RECORD
