Metadata-Version: 2.4
Name: quantflow-finance
Version: 0.1.10
Summary: Professional quantitative finance library for options pricing, risk analytics, and portfolio management
Home-page: https://github.com/jeevanba273/quantflow-finance
Author: Jeevan B A
Author-email: jeevanba273@gmail.com
License: MIT License
Project-URL: Bug Reports, https://github.com/jeevanba273/quantflow-finance/issues
Project-URL: Source, https://github.com/jeevanba273/quantflow-finance
Project-URL: Documentation, https://github.com/jeevanba273/quantflow-finance#readme
Keywords: quantitative finance,options pricing,risk management,black-scholes,portfolio analysis,financial engineering,derivatives,VaR,market data
Classifier: Development Status :: 4 - Beta
Classifier: Intended Audience :: Developers
Classifier: Intended Audience :: Education
Classifier: Intended Audience :: Science/Research
Classifier: Intended Audience :: Financial and Insurance Industry
Classifier: License :: OSI Approved :: MIT License
Classifier: Operating System :: OS Independent
Classifier: Programming Language :: Python :: 3
Classifier: Programming Language :: Python :: 3.8
Classifier: Programming Language :: Python :: 3.9
Classifier: Programming Language :: Python :: 3.10
Classifier: Programming Language :: Python :: 3.11
Classifier: Programming Language :: Python :: 3.12
Classifier: Programming Language :: Python :: 3.13
Classifier: Topic :: Office/Business :: Financial
Classifier: Topic :: Office/Business :: Financial :: Investment
Classifier: Topic :: Scientific/Engineering :: Mathematics
Classifier: Topic :: Scientific/Engineering :: Information Analysis
Classifier: Topic :: Software Development :: Libraries :: Python Modules
Requires-Python: >=3.8
License-File: LICENSE
Requires-Dist: numpy>=1.20.0
Requires-Dist: scipy>=1.7.0
Requires-Dist: pandas>=1.3.0
Requires-Dist: matplotlib>=3.3.0
Requires-Dist: yfinance>=0.1.70
Provides-Extra: dev
Requires-Dist: pytest>=6.0; extra == "dev"
Requires-Dist: black; extra == "dev"
Requires-Dist: flake8; extra == "dev"
Dynamic: author
Dynamic: author-email
Dynamic: classifier
Dynamic: description
Dynamic: description-content-type
Dynamic: home-page
Dynamic: keywords
Dynamic: license
Dynamic: license-file
Dynamic: project-url
Dynamic: provides-extra
Dynamic: requires-dist
Dynamic: requires-python
Dynamic: summary
